hub_sdk/__init__.py
hub_sdk/config.py
hub_sdk/hub_client.py
hub_sdk/base/__init__.py
hub_sdk/base/api_client.py
hub_sdk/base/auth.py
hub_sdk/base/crud_client.py
hub_sdk/base/paginated_list.py
hub_sdk/base/server_clients.py
hub_sdk/helpers/__init__.py
hub_sdk/helpers/error_handler.py
hub_sdk/helpers/exceptions.py
hub_sdk/helpers/logger.py
hub_sdk/helpers/utils.py
hub_sdk/modules/__init__.py
hub_sdk/modules/datasets.py
hub_sdk/modules/models.py
hub_sdk/modules/projects.py
hub_sdk/modules/teams.py
hub_sdk/modules/users.py
hub_sdk-0.0.24.dist-info/licenses/LICENSE
hub_sdk-0.0.24.dist-info/METADATA
hub_sdk-0.0.24.dist-info/WHEEL
hub_sdk-0.0.24.dist-info/top_level.txt
hub_sdk-0.0.24.dist-info/RECORD
